datalib/__init__.py
datalib_isimm-0.2.0.dist-info/METADATA
datalib_isimm-0.2.0.dist-info/WHEEL
datalib_isimm-0.2.0.dist-info/top_level.txt
datalib_isimm-0.2.0.dist-info/RECORD
